tests/test_memtable.py
tests/test_db.py
tests/__init__.py
tests/test_options.py
rocksdb/errors.py
rocksdb/_rocksdb.cpython-37m-x86_64-linux-gnu.so
rocksdb/_rocksdb.pypy37-pp73-x86_64-linux-gnu.so
rocksdb/interfaces.py
rocksdb/merge_operators.py
rocksdb/__init__.py
lbry_rocksdb-0.8.2.dist-info/RECORD
lbry_rocksdb-0.8.2.dist-info/LICENSE.md
lbry_rocksdb-0.8.2.dist-info/top_level.txt
lbry_rocksdb-0.8.2.dist-info/METADATA
lbry_rocksdb-0.8.2.dist-info/WHEEL
