Metadata-Version: 2.1
Name: lbry-rocksdb
Version: 0.8.2
Summary: Python bindings for RocksDB
Home-page: https://github.com/lbryio/lbry-rocksdb
Author: Jack Robison
Author-email: jackrobison@lbry.com
License: BSD License
Keywords: rocksdb,static,build
Platform: UNKNOWN
Requires-Python: >=3.7.0
License-File: LICENSE.md
Requires-Dist: setuptools (>=25)
Provides-Extra: doc
Requires-Dist: sphinx-rtd-theme ; extra == 'doc'
Requires-Dist: sphinx ; extra == 'doc'
